AUTHORS
LICENSE
MANIFEST.in
README.md
htmlcontact.py
setup.py
htmlcontact.egg-info/PKG-INFO
htmlcontact.egg-info/SOURCES.txt
htmlcontact.egg-info/dependency_links.txt
htmlcontact.egg-info/requires.txt
htmlcontact.egg-info/top_level.txt
test/test_search.py