Metadata-Version: 1.1
Name: htmlcontact
Version: 0.1
Summary: A simple python module to extract contact info from HTML pages
Home-page: http://github.com/tristantao/html-contact
Author: tristan tao
Author-email: tristan@teamleada.com
License: MIT
Platform: any
Classifier: Development Status :: 3 - Alpha
Classifier: Intended Audience :: Developers
Classifier: License :: OSI Approved :: MIT License
Classifier: Operating System :: OS Independent
Classifier: Programming Language :: Python
Classifier: Topic :: Software Development :: Libraries :: Python Modules
